CHANGES.rst
LICENSE.txt
MANIFEST.in
README.rst
setup.py
MediaCreek_WTForms_SQLAlchemy.egg-info/PKG-INFO
MediaCreek_WTForms_SQLAlchemy.egg-info/SOURCES.txt
MediaCreek_WTForms_SQLAlchemy.egg-info/dependency_links.txt
MediaCreek_WTForms_SQLAlchemy.egg-info/requires.txt
MediaCreek_WTForms_SQLAlchemy.egg-info/top_level.txt
docs/Makefile
docs/conf.py
docs/index.rst
docs/make.bat
docs/wtforms_sqlalchemy.rst
tests/__init__.py
tests/common.py
tests/requirements.txt
tests/tests.py
wtforms_sqlalchemy/__init__.py
wtforms_sqlalchemy/fields.py
wtforms_sqlalchemy/orm.py