Metadata-Version: 1.1
Name: MediaCreek-WTForms-SQLAlchemy
Version: 0.2
Summary: SQLAlchemy tools for WTForms
Home-page: https://github.com/MediaCreek/wtforms-sqlalchemy
Author: Thomas Johansson, James Crasta
Author-email: wtforms@simplecodes.com
License: BSD
Platform: UNKNOWN
Classifier: Development Status :: 5 - Production/Stable
Classifier: Environment :: Web Environment
Classifier: Intended Audience :: Developers
Classifier: License :: OSI Approved :: BSD License
Classifier: Operating System :: OS Independent
Classifier: Programming Language :: Python
Classifier: Programming Language :: Python :: 2.6
Classifier: Programming Language :: Python :: 2.7
Classifier: Programming Language :: Python :: 3
Classifier: Programming Language :: Python :: 3.3
Classifier: Programming Language :: Python :: 3.4
Classifier: Topic :: Internet :: WWW/HTTP :: Dynamic Content
Classifier: Topic :: Software Development :: Libraries :: Python Modules
